youqu_button_center/__init__.py
youqu_button_center/__version__.py
youqu_button_center/conf.py
youqu_button_center/install_depends.py
youqu_button_center/wayland_wininfo.py
youqu_button_center-2024.6.21.dist-info/METADATA
youqu_button_center-2024.6.21.dist-info/WHEEL
youqu_button_center-2024.6.21.dist-info/licenses/LICENSE
youqu_button_center-2024.6.21.dist-info/RECORD
