Metadata-Version: 2.1
Name: youqu-button-center
Version: 2024.6.21
Author-email: mikigo <huangmingqiang@uniontech.com>
License: GPL2.0
License-File: LICENSE
Requires-Python: >=3.7
Requires-Dist: funnylog
Requires-Dist: youqu-mousekey
